benders/__init__.py
benders/benders.py
BendersLib-0.0.1.dist-info/LICENSE
BendersLib-0.0.1.dist-info/METADATA
BendersLib-0.0.1.dist-info/WHEEL
BendersLib-0.0.1.dist-info/top_level.txt
BendersLib-0.0.1.dist-info/RECORD
