Metadata-Version: 2.1
Name: BendersLib
Version: 0.0.1
Summary: A Bender's decomposition library.
Home-page: https://guo.ph/benderslib
Author: Penghui Guo
Author-email: m@guo.ph
License: GPL-3.0
Platform: UNKNOWN
